kalepy/VERSION.txt
kalepy/__init__.py
kalepy/__main__.py
kalepy/kde.py
kalepy/kernels.py
kalepy/plot.py
kalepy/sample.py
kalepy/speed_test.py
kalepy/utils.py
kalepy/tests/__init__.py
kalepy/tests/test_distributions.py
kalepy/tests/test_kde.py
kalepy/tests/test_kernels.py
kalepy/tests/test_sample.py
kalepy/tests/test_utils.py
kalepy/tests/performance/performance.py
kalepy/tests/performance/pt-0.1/pt-0.1.npz
kalepy/tests/performance/pt-0.1/test.py
kalepy-1.4.3.dist-info/LICENSE
kalepy-1.4.3.dist-info/METADATA
kalepy-1.4.3.dist-info/WHEEL
kalepy-1.4.3.dist-info/top_level.txt
kalepy-1.4.3.dist-info/RECORD
