Metadata-Version: 2.1
Name: kalepy
Version: 1.4.3
Summary: Kernel Density Estimation (KDE) and sampling.
Home-page: https://github.com/lzkelley/kalepy/
Download-URL: https://github.com/lzkelley/kalepy/archive/v1.4.3.tar.gz
Author: Luke Zoltan Kelley
Author-email: lzkelley@northwestern.edu
License: MIT
Keywords: utilities,physics,astronomy,cosmology,astrophysics,statistics,kernel density estimation,kernel density estimate
Requires-Python: >=3.7
License-File: LICENSE
Requires-Dist: numpy
Requires-Dist: scipy
Requires-Dist: six
Requires-Dist: matplotlib (>=3)
Requires-Dist: numba
